{
  "project_info": {
    "project_number": "776217393909",
    "firebase_url": "https://xplora-15a7b.firebaseio.com",
    "project_id": "xplora-15a7b",
    "storage_bucket": "xplora-15a7b.appspot.com"
  },
  "client": [
    {
      "client_info": {
        "mobilesdk_app_id": "1:776217393909:android:424a9e4bc3041fcd",
        "android_client_info": {
          "package_name": "com.example.memovaradegante.xploraapp"
        }
      },
      "oauth_client": [
        {
          "client_id": "776217393909-l5lbmi30sp1ss1a3l2jbc3ljuqce1qvj.apps.googleusercontent.com",
          "client_type": 3
        }
      ],
      "api_key": [
        {
          "current_key": "AIzaSyAOlSifLUb4KdpCNR3qWK3ZaAopQyfvj5I"
        }
      ],
      "services": {
        "analytics_service": {
          "status": 1
        },
        "appinvite_service": {
          "status": 1,
          "other_platform_oauth_client": []
        },
        "ads_service": {
          "status": 2
        }
      }
    }
  ],
  "configuration_version": "1"
}